flask_mercure_sse/__init__.py
flask_mercure_sse/cli.py
flask_mercure_sse/ext.py
flask_mercure_sse/hub.py
flask_mercure_sse/server/__main__.py
flask_mercure_sse/server/app.py
flask_mercure_sse/server/wsgi.py
flask_mercure_sse-0.4.1.dist-info/WHEEL
flask_mercure_sse-0.4.1.dist-info/METADATA
flask_mercure_sse-0.4.1.dist-info/RECORD
