Metadata-Version: 2.4
Name: flask-mercure-sse
Version: 0.4.1
Summary: Server Sent Events (SSE) for Flask using the Mercure protocol
Author: Maxime Bouroumeau-Fuseau
Author-email: Maxime Bouroumeau-Fuseau <maxime.bouroumeau@gmail.com>
License-Expression: MIT
Requires-Dist: flask>=3.0.0,<4.0.0
Requires-Dist: requests>=2.31.0,<3.0.0
Requires-Dist: pyjwt>=2.8.0,<3.0.0
Requires-Dist: gevent>=25.9.1
Requires-Dist: python-dotenv>=1.1.1
Requires-Python: >=3.10
Project-URL: Repository, https://github.com/hyperflask/flask-mercure-sse
